{"hand_strength_limits":{"preflop":[45,56,60,65],"flop":[45,62,69,80],"turn":[55,65,80,85],"river":[55,65,80,85]},"stage_decisions":{"1":{"default_answer":{"coefficient":"tc","multiplier":0.0},"first_raise":{"coefficient":"fr","multiplier":0.0},"max_call_amount":{"coefficient":"bb","multiplier":0.1},"reraise_border":{"coefficient":"bb","multiplier":0.0},"reraise_answer":{"coefficient":"fr","multiplier":0.0}},"2":{"default_answer":{"coefficient":"tc","multiplier":0.0},"first_raise":{"coefficient":"tc","multiplier":1.0},"max_call_amount":{"coefficient":"bb","multiplier":1.0},"reraise_border":{"coefficient":"pr","multiplier":1.0},"reraise_answer":{"coefficient":"tc","multiplier":0.0}},"3":{"default_answer":{"coefficient":"tc","multiplier":1.0},"first_raise":{"coefficient":"fr","multiplier":2.0},"max_call_amount":{"coefficient":"bb","multiplier":4.0},"reraise_border":{"coefficient":"pr","multiplier":1.0},"reraise_answer":{"coefficient":"tc","multiplier":1.0}},"4":{"default_answer":{"coefficient":"p","multiplier":0.5},"first_raise":{"coefficient":"fr","multiplier":2.0},"max_call_amount":{"coefficient":"bb","multiplier":7.0},"reraise_border":{"coefficient":"s","multiplier":1.0},"reraise_answer":{"coefficient":"tc","multiplier":1.0}},"5":{"default_answer":{"coefficient":"p","multiplier":0.66},"first_raise":{"coefficient":"bb","multiplier":2.0},"max_call_amount":{"coefficient":"s","multiplier":1.0},"reraise_border":{"coefficient":"s","multiplier":1.0},"reraise_answer":{"coefficient":"fr","multiplier":2.0}}},"is_adaptive":false,"final_emotion_percent":7,"game_emotion_percent":10}